MANIFEST.in
README.txt
setup.cfg
setup.py
collective/__init__.py
collective.z3cform.phonewidget.egg-info/PKG-INFO
collective.z3cform.phonewidget.egg-info/SOURCES.txt
collective.z3cform.phonewidget.egg-info/dependency_links.txt
collective.z3cform.phonewidget.egg-info/entry_points.txt
collective.z3cform.phonewidget.egg-info/namespace_packages.txt
collective.z3cform.phonewidget.egg-info/not-zip-safe
collective.z3cform.phonewidget.egg-info/paster_plugins.txt
collective.z3cform.phonewidget.egg-info/requires.txt
collective.z3cform.phonewidget.egg-info/top_level.txt
collective/z3cform/__init__.py
collective/z3cform/phonewidget/__init__.py
collective/z3cform/phonewidget/configure.zcml
collective/z3cform/phonewidget/interfaces.py
collective/z3cform/phonewidget/browser/__init__.py
collective/z3cform/phonewidget/browser/configure.zcml
collective/z3cform/phonewidget/browser/widget.py
collective/z3cform/phonewidget/browser/templates/phone_input.pt
collective/z3cform/phonewidget/locales/collective.z3cform.phonewidget-extra.pot
collective/z3cform/phonewidget/locales/collective.z3cform.phonewidget.pot
collective/z3cform/phonewidget/locales/update.sh
collective/z3cform/phonewidget/locales/en/LC_MESSAGES/collective.z3cform.phonewidget.mo
collective/z3cform/phonewidget/locales/en/LC_MESSAGES/collective.z3cform.phonewidget.po
collective/z3cform/phonewidget/locales/fr/LC_MESSAGES/collective.z3cform.phonewidget.mo
collective/z3cform/phonewidget/locales/fr/LC_MESSAGES/collective.z3cform.phonewidget.po